<map>
  <entry>
    <string>plugin_identifier</string>
    <string>org.lockss.plugin.highwire.HighWireTriggeredPlugin</string>
  </entry>
  <entry>
    <string>plugin_version</string>
    <string>2</string>
  </entry>
  <entry>
    <string>plugin_parent</string>
    <string>org.lockss.plugin.highwire.HighWirePressPlugin</string>
  </entry>
   <entry>
    <string>plugin_parent_version</string>
    <string>79</string>
  </entry>
  <entry>
    <string>plugin_name</string>
    <string>HighWirePlugin Content (LOCKSS Triggered Content)</string>
  </entry>
  <entry>
   <string>au_name</string>
   <string>&quot;HighWire Plugin (H10c for Triggered Content), Base URL %s, Volume %s&quot;, base_url, volume_name </string>
  </entry>
  <entry>
    <string>au_permission_url</string>
    <string>&quot;%slockss-permission.html&quot;,base_url</string>
  </entry>
  <entry>
    <string>au_start_url</string>
    <string>&quot;%sclockss-manifest/vol_%s_manifest.dtl&quot;, base_url, volume_name</string>
  </entry>
  <entry>
    <string>au_permission_checker_factory</string>
    <string>org.lockss.plugin.highwire.TriggeredHighWirePermissionCheckerFactory</string>
  </entry>
</map>